README.md
setup.cfg
setup.py
started/__init__.py
started.egg-info/PKG-INFO
started.egg-info/SOURCES.txt
started.egg-info/dependency_links.txt
started.egg-info/top_level.txt