Metadata-Version: 1.1
Name: started
Version: 0.1
Summary: Subprocess-based lib for integration tests
Home-page: https://github.com/eugene-katsevman/started
Author: Eugene Katsevman
Author-email: eugene.katsevman@gmail.com
License: UNKNOWN
Download-URL: https://github.com/eugene-katsevman/started/archive/0.1.tar.gz
Keywords: testing,integration
Platform: UNKNOWN
